{"level":16,"maxWave":6,"propList":[{"wave":1,"propType":3,"colorInt":0,"oriY":0.0,"pos":{"X":2.9483285,"Y":0.0,"Z":3.85144043},"scale":{"X":1.0,"Y":1.0,"Z":1.0},"angle":{"X":0.0,"Y":0.0,"Z":0.0},"rotation":{"X":0.0,"Y":0.0,"Z":0.0},"revolution":{"X":0.0,"Y":0.0,"Z":0.0},"revolutionCenter":{"X":0.0,"Y":0.0,"Z":0.0},"yMove":{"X":0.0,"Y":0.0,"Z":0.0},"xMove":{"X":0.0,"Y":0.0,"Z":0.0},"yScale":{"X":0.0,"Y":0.0,"Z":0.0},"xzScale":{"X":0.0,"Y":0.0,"Z":0.0},"paths":[],"pathV":{"X":0.0,"Y":0.0,"Z":0.0},"isStatic":true},{"wave":1,"propType":3,"colorInt":0,"oriY":0.0,"pos":{"X":2.593718,"Y":0.0,"Z":3.39247131},"scale":{"X":1.0,"Y":1.0,"Z":1.0},"angle":{"X":0.0,"Y":0.0,"Z":0.0},"rotation":{"X":0.0,"Y":0.0,"Z":0.0},"revolution":{"X":0.0,"Y":0.0,"Z":0.0},"revolutionCenter":{"X":0.0,"Y":0.0,"Z":0.0},"yMove":{"X":0.0,"Y":0.0,"Z":0.0},"xMove":{"X":0.0,"Y":0.0,"Z":0.0},"yScale":{"X":0.0,"Y":0.0,"Z":0.0},"xzScale":{"X":0.0,"Y":0.0,"Z":0.0},"paths":[],"pathV":{"X":0.0,"Y":0.0,"Z":0.0},"isStatic":true},{"wave":1,"propType":3,"colorInt":0,"oriY":0.0,"pos":{"X":-0.222897932,"Y":0.0,"Z":-1.22724915},"scale":{"X":0.5,"Y":0.5,"Z":0.5},"angle":{"X":0.0,"Y":0.0,"Z":0.0},"rotation":{"X":0.0,"Y":0.0,"Z":0.0},"revolution":{"X":0.0,"Y":0.0,"Z":0.0},"revolutionCenter":{"X":0.0,"Y":0.0,"Z":0.0},"yMove":{"X":0.0,"Y":0.0,"Z":0.0},"xMove":{"X":0.0,"Y":0.0,"Z":0.0},"yScale":{"X":0.0,"Y":0.0,"Z":0.0},"xzScale":{"X":0.0,"Y":0.0,"Z":0.0},"paths":[],"pathV":{"X":0.0,"Y":0.0,"Z":0.0},"isStatic":true},{"wave":1,"propType":3,"colorInt":0,"oriY":0.0,"pos":{"X":-2.95845985,"Y":0.0,"Z":-5.148514},"scale":{"X":1.0,"Y":1.0,"Z":1.0},"angle":{"X":0.0,"Y":0.0,"Z":0.0},"rotation":{"X":0.0,"Y":0.0,"Z":0.0},"revolution":{"X":0.0,"Y":0.0,"Z":0.0},"revolutionCenter":{"X":0.0,"Y":0.0,"Z":0.0},"yMove":{"X":0.0,"Y":0.0,"Z":0.0},"xMove":{"X":0.0,"Y":0.0,"Z":0.0},"yScale":{"X":0.0,"Y":0.0,"Z":0.0},"xzScale":{"X":0.0,"Y":0.0,"Z":0.0},"paths":[],"pathV":{"X":0.0,"Y":0.0,"Z":0.0},"isStatic":true},{"wave":1,"propType":3,"colorInt":0,"oriY":0.0,"pos":{"X":-3.35276127E-07,"Y":0.0,"Z":-0.9479065},"scale":{"X":1.0,"Y":1.0,"Z":1.0},"angle":{"X":0.0,"Y":0.0,"Z":0.0},"rotation":{"X":0.0,"Y":0.0,"Z":0.0},"revolution":{"X":0.0,"Y":0.0,"Z":0.0},"revolutionCenter":{"X":0.0,"Y":0.0,"Z":0.0},"yMove":{"X":0.0,"Y":0.0,"Z":0.0},"xMove":{"X":0.0,"Y":0.0,"Z":0.0},"yScale":{"X":0.0,"Y":0.0,"Z":0.0},"xzScale":{"X":0.0,"Y":0.0,"Z":0.0},"paths":[],"pathV":{"X":0.0,"Y":0.0,"Z":0.0},"isStatic":true},{"wave":1,"propType":3,"colorInt":0,"oriY":0.0,"pos":{"X":0.303950965,"Y":0.0,"Z":-0.608657837},"scale":{"X":1.0,"Y":1.0,"Z":1.0},"angle":{"X":0.0,"Y":0.0,"Z":0.0},"rotation":{"X":0.0,"Y":0.0,"Z":0.0},"revolution":{"X":0.0,"Y":0.0,"Z":0.0},"revolutionCenter":{"X":0.0,"Y":0.0,"Z":0.0},"yMove":{"X":0.0,"Y":0.0,"Z":0.0},"xMove":{"X":0.0,"Y":0.0,"Z":0.0},"yScale":{"X":0.0,"Y":0.0,"Z":0.0},"xzScale":{"X":0.0,"Y":0.0,"Z":0.0},"paths":[],"pathV":{"X":0.0,"Y":0.0,"Z":0.0},"isStatic":true},{"wave":1,"propType":3,"colorInt":0,"oriY":0.0,"pos":{"X":0.597770452,"Y":0.0,"Z":-0.249435425},"scale":{"X":1.0,"Y":1.0,"Z":1.0},"angle":{"X":0.0,"Y":0.0,"Z":0.0},"rotation":{"X":0.0,"Y":0.0,"Z":0.0},"revolution":{"X":0.0,"Y":0.0,"Z":0.0},"revolutionCenter":{"X":0.0,"Y":0.0,"Z":0.0},"yMove":{"X":0.0,"Y":0.0,"Z":0.0},"xMove":{"X":0.0,"Y":0.0,"Z":0.0},"yScale":{"X":0.0,"Y":0.0,"Z":0.0},"xzScale":{"X":0.0,"Y":0.0,"Z":0.0},"paths":[],"pathV":{"X":0.0,"Y":0.0,"Z":0.0},"isStatic":true},{"wave":1,"propType":3,"colorInt":0,"oriY":0.0,"pos":{"X":2.86727452,"Y":0.0,"Z":-2.17515564},"scale":{"X":1.0,"Y":1.0,"Z":1.0},"angle":{"X":0.0,"Y":0.0,"Z":0.0},"rotation":{"X":0.0,"Y":0.0,"Z":0.0},"revolution":{"X":0.0,"Y":0.0,"Z":0.0},"revolutionCenter":{"X":0.0,"Y":0.0,"Z":0.0},"yMove":{"X":0.0,"Y":0.0,"Z":0.0},"xMove":{"X":0.0,"Y":0.0,"Z":0.0},"yScale":{"X":0.0,"Y":0.0,"Z":0.0},"xzScale":{"X":0.0,"Y":0.0,"Z":0.0},"paths":[],"pathV":{"X":0.0,"Y":0.0,"Z":0.0},"isStatic":true},{"wave":1,"propType":3,"colorInt":0,"oriY":0.0,"pos":{"X":-2.80648422,"Y":0.0,"Z":-2.77384949},"scale":{"X":1.0,"Y":1.0,"Z":1.0},"angle":{"X":0.0,"Y":0.0,"Z":0.0},"rotation":{"X":0.0,"Y":0.0,"Z":0.0},"revolution":{"X":0.0,"Y":0.0,"Z":0.0},"revolutionCenter":{"X":0.0,"Y":0.0,"Z":0.0},"yMove":{"X":0.0,"Y":0.0,"Z":0.0},"xMove":{"X":0.0,"Y":0.0,"Z":0.0},"yScale":{"X":0.0,"Y":0.0,"Z":0.0},"xzScale":{"X":0.0,"Y":0.0,"Z":0.0},"paths":[],"pathV":{"X":0.0,"Y":0.0,"Z":0.0},"isStatic":true},{"wave":1,"propType":3,"colorInt":0,"oriY":0.0,"pos":{"X":2.90780139,"Y":0.0,"Z":-1.36694336},"scale":{"X":1.0,"Y":1.0,"Z":1.0},"angle":{"X":0.0,"Y":0.0,"Z":0.0},"rotation":{"X":0.0,"Y":0.0,"Z":0.0},"revolution":{"X":0.0,"Y":0.0,"Z":0.0},"revolutionCenter":{"X":0.0,"Y":0.0,"Z":0.0},"yMove":{"X":0.0,"Y":0.0,"Z":0.0},"xMove":{"X":0.0,"Y":0.0,"Z":0.0},"yScale":{"X":0.0,"Y":0.0,"Z":0.0},"xzScale":{"X":0.0,"Y":0.0,"Z":0.0},"paths":[],"pathV":{"X":0.0,"Y":0.0,"Z":0.0},"isStatic":true},{"wave":1,"propType":6,"colorInt":0,"oriY":0.0,"pos":{"X":-2.88753867,"Y":0.0,"Z":1.3669281},"scale":{"X":1.0,"Y":1.0,"Z":1.0},"angle":{"X":0.0,"Y":0.0,"Z":0.0},"rotation":{"X":0.0,"Y":0.0,"Z":0.0},"revolution":{"X":0.0,"Y":0.0,"Z":0.0},"revolutionCenter":{"X":0.0,"Y":0.0,"Z":0.0},"yMove":{"X":0.0,"Y":0.0,"Z":0.0},"xMove":{"X":0.0,"Y":0.0,"Z":0.0},"yScale":{"X":0.0,"Y":0.0,"Z":0.0},"xzScale":{"X":0.0,"Y":0.0,"Z":0.0},"paths":[],"pathV":{"X":0.0,"Y":0.0,"Z":0.0},"isStatic":true},{"wave":1,"propType":0,"colorInt":0,"oriY":0.0,"pos":{"X":-0.5471123,"Y":0.0,"Z":4.699524},"scale":{"X":1.0,"Y":1.0,"Z":1.0},"angle":{"X":0.0,"Y":0.0,"Z":0.0},"rotation":{"X":0.0,"Y":0.0,"Z":0.0},"revolution":{"X":0.0,"Y":0.0,"Z":0.0},"revolutionCenter":{"X":0.0,"Y":0.0,"Z":0.0},"yMove":{"X":0.0,"Y":0.0,"Z":0.0},"xMove":{"X":0.0,"Y":0.0,"Z":0.0},"yScale":{"X":0.0,"Y":0.0,"Z":0.0},"xzScale":{"X":0.0,"Y":0.0,"Z":0.0},"paths":[],"pathV":{"X":0.0,"Y":0.0,"Z":0.0},"isStatic":true},{"wave":1,"propType":2,"colorInt":0,"oriY":0.0,"pos":{"X":0.476190329,"Y":0.0,"Z":-5.1585083},"scale":{"X":1.0,"Y":1.0,"Z":1.0},"angle":{"X":0.0,"Y":0.0,"Z":0.0},"rotation":{"X":0.0,"Y":0.0,"Z":0.0},"revolution":{"X":0.0,"Y":0.0,"Z":0.0},"revolutionCenter":{"X":0.0,"Y":0.0,"Z":0.0},"yMove":{"X":0.0,"Y":0.0,"Z":0.0},"xMove":{"X":0.0,"Y":0.0,"Z":0.0},"yScale":{"X":0.0,"Y":0.0,"Z":0.0},"xzScale":{"X":0.0,"Y":0.0,"Z":0.0},"paths":[],"pathV":{"X":0.0,"Y":0.0,"Z":0.0},"isStatic":true},{"wave":7,"propType":1,"colorInt":0,"oriY":0.0,"pos":{"X":0.486322224,"Y":0.0,"Z":-4.699539},"scale":{"X":1.0,"Y":1.0,"Z":1.0},"angle":{"X":0.0,"Y":0.0,"Z":0.0},"rotation":{"X":0.0,"Y":0.0,"Z":0.0},"revolution":{"X":0.0,"Y":0.0,"Z":0.0},"revolutionCenter":{"X":0.0,"Y":0.0,"Z":0.0},"yMove":{"X":0.0,"Y":0.0,"Z":0.0},"xMove":{"X":0.0,"Y":0.0,"Z":0.0},"yScale":{"X":0.0,"Y":0.0,"Z":0.0},"xzScale":{"X":0.0,"Y":0.0,"Z":0.0},"paths":[],"pathV":{"X":0.0,"Y":0.0,"Z":0.0},"isStatic":true}],"waveList":[{"wave":1,"propList":[{"wave":1,"propType":8,"colorInt":0,"oriY":0.14,"pos":{"X":-0.9827761,"Y":0.14,"Z":0.638565063},"scale":{"X":1.0,"Y":1.0,"Z":1.0},"angle":{"X":0.0,"Y":0.0,"Z":0.0},"rotation":{"X":0.0,"Y":0.0,"Z":0.0},"revolution":{"X":0.0,"Y":0.0,"Z":0.0},"revolutionCenter":{"X":0.0,"Y":0.0,"Z":0.0},"yMove":{"X":0.0,"Y":0.0,"Z":0.0},"xMove":{"X":0.0,"Y":0.0,"Z":0.0},"yScale":{"X":0.0,"Y":0.0,"Z":0.0},"xzScale":{"X":0.0,"Y":0.0,"Z":0.0},"paths":[],"pathV":{"X":0.0,"Y":0.0,"Z":0.0},"isStatic":false},{"wave":1,"propType":8,"colorInt":0,"oriY":0.14,"pos":{"X":-1.236069,"Y":0.14,"Z":0.0299377441},"scale":{"X":1.0,"Y":1.0,"Z":1.0},"angle":{"X":0.0,"Y":0.0,"Z":0.0},"rotation":{"X":0.0,"Y":0.0,"Z":0.0},"revolution":{"X":0.0,"Y":0.0,"Z":0.0},"revolutionCenter":{"X":0.0,"Y":0.0,"Z":0.0},"yMove":{"X":0.0,"Y":0.0,"Z":0.0},"xMove":{"X":0.0,"Y":0.0,"Z":0.0},"yScale":{"X":0.0,"Y":0.0,"Z":0.0},"xzScale":{"X":0.0,"Y":0.0,"Z":0.0},"paths":[],"pathV":{"X":0.0,"Y":0.0,"Z":0.0},"isStatic":false},{"wave":1,"propType":8,"colorInt":0,"oriY":0.14,"pos":{"X":-1.42857182,"Y":0.14,"Z":-0.5587616},"scale":{"X":1.0,"Y":1.0,"Z":1.0},"angle":{"X":0.0,"Y":0.0,"Z":0.0},"rotation":{"X":0.0,"Y":0.0,"Z":0.0},"revolution":{"X":0.0,"Y":0.0,"Z":0.0},"revolutionCenter":{"X":0.0,"Y":0.0,"Z":0.0},"yMove":{"X":0.0,"Y":0.0,"Z":0.0},"xMove":{"X":0.0,"Y":0.0,"Z":0.0},"yScale":{"X":0.0,"Y":0.0,"Z":0.0},"xzScale":{"X":0.0,"Y":0.0,"Z":0.0},"paths":[],"pathV":{"X":0.0,"Y":0.0,"Z":0.0},"isStatic":false}]},{"wave":2,"propList":[{"wave":2,"propType":8,"colorInt":0,"oriY":0.14,"pos":{"X":0.628166139,"Y":0.14,"Z":-2.16517639},"scale":{"X":1.0,"Y":1.0,"Z":1.0},"angle":{"X":0.0,"Y":0.0,"Z":0.0},"rotation":{"X":0.0,"Y":0.0,"Z":0.0},"revolution":{"X":0.0,"Y":0.0,"Z":0.0},"revolutionCenter":{"X":0.0,"Y":0.0,"Z":0.0},"yMove":{"X":0.0,"Y":0.0,"Z":0.0},"xMove":{"X":0.0,"Y":0.0,"Z":0.0},"yScale":{"X":0.0,"Y":0.0,"Z":0.0},"xzScale":{"X":0.0,"Y":0.0,"Z":0.0},"paths":[],"pathV":{"X":0.0,"Y":0.0,"Z":0.0},"isStatic":false},{"wave":2,"propType":8,"colorInt":0,"oriY":0.14,"pos":{"X":0.9422493,"Y":0.14,"Z":-1.65632629},"scale":{"X":1.0,"Y":1.0,"Z":1.0},"angle":{"X":0.0,"Y":0.0,"Z":0.0},"rotation":{"X":0.0,"Y":0.0,"Z":0.0},"revolution":{"X":0.0,"Y":0.0,"Z":0.0},"revolutionCenter":{"X":0.0,"Y":0.0,"Z":0.0},"yMove":{"X":0.0,"Y":0.0,"Z":0.0},"xMove":{"X":0.0,"Y":0.0,"Z":0.0},"yScale":{"X":0.0,"Y":0.0,"Z":0.0},"xzScale":{"X":0.0,"Y":0.0,"Z":0.0},"paths":[],"pathV":{"X":0.0,"Y":0.0,"Z":0.0},"isStatic":false},{"wave":2,"propType":8,"colorInt":0,"oriY":0.14,"pos":{"X":1.27659571,"Y":0.14,"Z":-1.12750244},"scale":{"X":1.0,"Y":1.0,"Z":1.0},"angle":{"X":0.0,"Y":0.0,"Z":0.0},"rotation":{"X":0.0,"Y":0.0,"Z":0.0},"revolution":{"X":0.0,"Y":0.0,"Z":0.0},"revolutionCenter":{"X":0.0,"Y":0.0,"Z":0.0},"yMove":{"X":0.0,"Y":0.0,"Z":0.0},"xMove":{"X":0.0,"Y":0.0,"Z":0.0},"yScale":{"X":0.0,"Y":0.0,"Z":0.0},"xzScale":{"X":0.0,"Y":0.0,"Z":0.0},"paths":[],"pathV":{"X":0.0,"Y":0.0,"Z":0.0},"isStatic":false}]},{"wave":3,"propList":[{"wave":3,"propType":8,"colorInt":0,"oriY":0.14,"pos":{"X":-1.52988875,"Y":0.14,"Z":-0.927932739},"scale":{"X":1.0,"Y":1.0,"Z":1.0},"angle":{"X":0.0,"Y":0.0,"Z":0.0},"rotation":{"X":0.0,"Y":0.0,"Z":0.0},"revolution":{"X":0.0,"Y":0.0,"Z":0.0},"revolutionCenter":{"X":0.0,"Y":0.0,"Z":0.0},"yMove":{"X":0.0,"Y":0.0,"Z":0.0},"xMove":{"X":0.0,"Y":0.0,"Z":0.0},"yScale":{"X":0.0,"Y":0.0,"Z":0.0},"xzScale":{"X":0.0,"Y":0.0,"Z":0.0},"paths":[],"pathV":{"X":0.0,"Y":0.0,"Z":0.0},"isStatic":false},{"wave":3,"propType":8,"colorInt":0,"oriY":0.14,"pos":{"X":-1.30699086,"Y":0.14,"Z":-0.5088959},"scale":{"X":1.0,"Y":1.0,"Z":1.0},"angle":{"X":0.0,"Y":0.0,"Z":0.0},"rotation":{"X":0.0,"Y":0.0,"Z":0.0},"revolution":{"X":0.0,"Y":0.0,"Z":0.0},"revolutionCenter":{"X":0.0,"Y":0.0,"Z":0.0},"yMove":{"X":0.0,"Y":0.0,"Z":0.0},"xMove":{"X":0.0,"Y":0.0,"Z":0.0},"yScale":{"X":0.0,"Y":0.0,"Z":0.0},"xzScale":{"X":0.0,"Y":0.0,"Z":0.0},"paths":[],"pathV":{"X":0.0,"Y":0.0,"Z":0.0},"isStatic":false},{"wave":3,"propType":8,"colorInt":0,"oriY":0.14,"pos":{"X":-1.023303,"Y":0.14,"Z":-0.0299377441},"scale":{"X":1.0,"Y":1.0,"Z":1.0},"angle":{"X":0.0,"Y":0.0,"Z":0.0},"rotation":{"X":0.0,"Y":0.0,"Z":0.0},"revolution":{"X":0.0,"Y":0.0,"Z":0.0},"revolutionCenter":{"X":0.0,"Y":0.0,"Z":0.0},"yMove":{"X":0.0,"Y":0.0,"Z":0.0},"xMove":{"X":0.0,"Y":0.0,"Z":0.0},"yScale":{"X":0.0,"Y":0.0,"Z":0.0},"xzScale":{"X":0.0,"Y":0.0,"Z":0.0},"paths":[],"pathV":{"X":0.0,"Y":0.0,"Z":0.0},"isStatic":false},{"wave":3,"propType":8,"colorInt":0,"oriY":0.14,"pos":{"X":-0.7598787,"Y":0.14,"Z":0.379165649},"scale":{"X":1.0,"Y":1.0,"Z":1.0},"angle":{"X":0.0,"Y":0.0,"Z":0.0},"rotation":{"X":0.0,"Y":0.0,"Z":0.0},"revolution":{"X":0.0,"Y":0.0,"Z":0.0},"revolutionCenter":{"X":0.0,"Y":0.0,"Z":0.0},"yMove":{"X":0.0,"Y":0.0,"Z":0.0},"xMove":{"X":0.0,"Y":0.0,"Z":0.0},"yScale":{"X":0.0,"Y":0.0,"Z":0.0},"xzScale":{"X":0.0,"Y":0.0,"Z":0.0},"paths":[],"pathV":{"X":0.0,"Y":0.0,"Z":0.0},"isStatic":false}]},{"wave":4,"propList":[{"wave":4,"propType":8,"colorInt":0,"oriY":0.14,"pos":{"X":0.4457952,"Y":0.14,"Z":-2.27494812},"scale":{"X":1.0,"Y":1.0,"Z":1.0},"angle":{"X":0.0,"Y":0.0,"Z":0.0},"rotation":{"X":0.0,"Y":0.0,"Z":0.0},"revolution":{"X":0.0,"Y":0.0,"Z":0.0},"revolutionCenter":{"X":0.0,"Y":0.0,"Z":0.0},"yMove":{"X":0.0,"Y":0.0,"Z":0.0},"xMove":{"X":0.0,"Y":0.0,"Z":0.0},"yScale":{"X":0.0,"Y":0.0,"Z":0.0},"xzScale":{"X":0.0,"Y":0.0,"Z":0.0},"paths":[],"pathV":{"X":0.0,"Y":0.0,"Z":0.0},"isStatic":false},{"wave":4,"propType":8,"colorInt":0,"oriY":0.14,"pos":{"X":0.7801418,"Y":0.14,"Z":-1.825943},"scale":{"X":1.0,"Y":1.0,"Z":1.0},"angle":{"X":0.0,"Y":0.0,"Z":0.0},"rotation":{"X":0.0,"Y":0.0,"Z":0.0},"revolution":{"X":0.0,"Y":0.0,"Z":0.0},"revolutionCenter":{"X":0.0,"Y":0.0,"Z":0.0},"yMove":{"X":0.0,"Y":0.0,"Z":0.0},"xMove":{"X":0.0,"Y":0.0,"Z":0.0},"yScale":{"X":0.0,"Y":0.0,"Z":0.0},"xzScale":{"X":0.0,"Y":0.0,"Z":0.0},"paths":[],"pathV":{"X":0.0,"Y":0.0,"Z":0.0},"isStatic":false},{"wave":4,"propType":8,"colorInt":0,"oriY":0.14,"pos":{"X":1.16514671,"Y":0.14,"Z":-1.29708862},"scale":{"X":1.0,"Y":1.0,"Z":1.0},"angle":{"X":0.0,"Y":0.0,"Z":0.0},"rotation":{"X":0.0,"Y":0.0,"Z":0.0},"revolution":{"X":0.0,"Y":0.0,"Z":0.0},"revolutionCenter":{"X":0.0,"Y":0.0,"Z":0.0},"yMove":{"X":0.0,"Y":0.0,"Z":0.0},"xMove":{"X":0.0,"Y":0.0,"Z":0.0},"yScale":{"X":0.0,"Y":0.0,"Z":0.0},"xzScale":{"X":0.0,"Y":0.0,"Z":0.0},"paths":[],"pathV":{"X":0.0,"Y":0.0,"Z":0.0},"isStatic":false},{"wave":4,"propType":8,"colorInt":0,"oriY":0.14,"pos":{"X":1.59067869,"Y":0.14,"Z":-0.668487549},"scale":{"X":1.0,"Y":1.0,"Z":1.0},"angle":{"X":0.0,"Y":0.0,"Z":0.0},"rotation":{"X":0.0,"Y":0.0,"Z":0.0},"revolution":{"X":0.0,"Y":0.0,"Z":0.0},"revolutionCenter":{"X":0.0,"Y":0.0,"Z":0.0},"yMove":{"X":0.0,"Y":0.0,"Z":0.0},"xMove":{"X":0.0,"Y":0.0,"Z":0.0},"yScale":{"X":0.0,"Y":0.0,"Z":0.0},"xzScale":{"X":0.0,"Y":0.0,"Z":0.0},"paths":[],"pathV":{"X":0.0,"Y":0.0,"Z":0.0},"isStatic":false}]},{"wave":5,"propList":[{"wave":5,"propType":10,"colorInt":0,"oriY":0.0,"pos":{"X":-0.5572442,"Y":0.0,"Z":1.00773621},"scale":{"X":1.0,"Y":1.0,"Z":1.0},"angle":{"X":0.0,"Y":0.0,"Z":0.0},"rotation":{"X":0.0,"Y":0.0,"Z":0.0},"revolution":{"X":0.0,"Y":0.0,"Z":0.0},"revolutionCenter":{"X":0.0,"Y":0.0,"Z":0.0},"yMove":{"X":0.0,"Y":0.0,"Z":0.0},"xMove":{"X":0.0,"Y":0.0,"Z":0.0},"yScale":{"X":0.0,"Y":0.0,"Z":0.0},"xzScale":{"X":0.0,"Y":0.0,"Z":0.0},"paths":[],"pathV":{"X":0.0,"Y":0.0,"Z":0.0},"isStatic":false},{"wave":5,"propType":8,"colorInt":0,"oriY":0.14,"pos":{"X":-0.78014195,"Y":0.14,"Z":0.289367676},"scale":{"X":1.0,"Y":1.0,"Z":1.0},"angle":{"X":0.0,"Y":0.0,"Z":0.0},"rotation":{"X":0.0,"Y":0.0,"Z":0.0},"revolution":{"X":0.0,"Y":0.0,"Z":0.0},"revolutionCenter":{"X":0.0,"Y":0.0,"Z":0.0},"yMove":{"X":0.0,"Y":0.0,"Z":0.0},"xMove":{"X":0.0,"Y":0.0,"Z":0.0},"yScale":{"X":0.0,"Y":0.0,"Z":0.0},"xzScale":{"X":0.0,"Y":0.0,"Z":0.0},"paths":[],"pathV":{"X":0.0,"Y":0.0,"Z":0.0},"isStatic":false},{"wave":5,"propType":8,"colorInt":0,"oriY":0.14,"pos":{"X":-1.205674,"Y":0.14,"Z":0.129730225},"scale":{"X":1.0,"Y":1.0,"Z":1.0},"angle":{"X":0.0,"Y":0.0,"Z":0.0},"rotation":{"X":0.0,"Y":0.0,"Z":0.0},"revolution":{"X":0.0,"Y":0.0,"Z":0.0},"revolutionCenter":{"X":0.0,"Y":0.0,"Z":0.0},"yMove":{"X":0.0,"Y":0.0,"Z":0.0},"xMove":{"X":0.0,"Y":0.0,"Z":0.0},"yScale":{"X":0.0,"Y":0.0,"Z":0.0},"xzScale":{"X":0.0,"Y":0.0,"Z":0.0},"paths":[],"pathV":{"X":0.0,"Y":0.0,"Z":0.0},"isStatic":false},{"wave":5,"propType":8,"colorInt":0,"oriY":0.14,"pos":{"X":-0.7497468,"Y":0.14,"Z":0.6984558},"scale":{"X":1.0,"Y":1.0,"Z":1.0},"angle":{"X":0.0,"Y":0.0,"Z":0.0},"rotation":{"X":0.0,"Y":0.0,"Z":0.0},"revolution":{"X":0.0,"Y":0.0,"Z":0.0},"revolutionCenter":{"X":0.0,"Y":0.0,"Z":0.0},"yMove":{"X":0.0,"Y":0.0,"Z":0.0},"xMove":{"X":0.0,"Y":0.0,"Z":0.0},"yScale":{"X":0.0,"Y":0.0,"Z":0.0},"xzScale":{"X":0.0,"Y":0.0,"Z":0.0},"paths":[],"pathV":{"X":0.0,"Y":0.0,"Z":0.0},"isStatic":false},{"wave":5,"propType":8,"colorInt":0,"oriY":0.14,"pos":{"X":-1.1347518,"Y":0.14,"Z":-0.289337158},"scale":{"X":1.0,"Y":1.0,"Z":1.0},"angle":{"X":0.0,"Y":0.0,"Z":0.0},"rotation":{"X":0.0,"Y":0.0,"Z":0.0},"revolution":{"X":0.0,"Y":0.0,"Z":0.0},"revolutionCenter":{"X":0.0,"Y":0.0,"Z":0.0},"yMove":{"X":0.0,"Y":0.0,"Z":0.0},"xMove":{"X":0.0,"Y":0.0,"Z":0.0},"yScale":{"X":0.0,"Y":0.0,"Z":0.0},"xzScale":{"X":0.0,"Y":0.0,"Z":0.0},"paths":[],"pathV":{"X":0.0,"Y":0.0,"Z":0.0},"isStatic":false},{"wave":5,"propType":8,"colorInt":0,"oriY":0.14,"pos":{"X":-1.60081077,"Y":0.14,"Z":-0.3991089},"scale":{"X":1.0,"Y":1.0,"Z":1.0},"angle":{"X":0.0,"Y":0.0,"Z":0.0},"rotation":{"X":0.0,"Y":0.0,"Z":0.0},"revolution":{"X":0.0,"Y":0.0,"Z":0.0},"revolutionCenter":{"X":0.0,"Y":0.0,"Z":0.0},"yMove":{"X":0.0,"Y":0.0,"Z":0.0},"xMove":{"X":0.0,"Y":0.0,"Z":0.0},"yScale":{"X":0.0,"Y":0.0,"Z":0.0},"xzScale":{"X":0.0,"Y":0.0,"Z":0.0},"paths":[],"pathV":{"X":0.0,"Y":0.0,"Z":0.0},"isStatic":false}]},{"wave":6,"propList":[{"wave":6,"propType":10,"colorInt":0,"oriY":0.0,"pos":{"X":0.0810536146,"Y":0.0,"Z":-2.4744873},"scale":{"X":1.0,"Y":1.0,"Z":1.0},"angle":{"X":0.0,"Y":0.0,"Z":0.0},"rotation":{"X":0.0,"Y":0.0,"Z":0.0},"revolution":{"X":0.0,"Y":0.0,"Z":0.0},"revolutionCenter":{"X":0.0,"Y":0.0,"Z":0.0},"yMove":{"X":0.0,"Y":0.0,"Z":0.0},"xMove":{"X":0.0,"Y":0.0,"Z":0.0},"yScale":{"X":0.0,"Y":0.0,"Z":0.0},"xzScale":{"X":0.0,"Y":0.0,"Z":0.0},"paths":[],"pathV":{"X":0.0,"Y":0.0,"Z":0.0},"isStatic":false},{"wave":6,"propType":8,"colorInt":0,"oriY":0.14,"pos":{"X":1.09422493,"Y":0.14,"Z":-1.845871},"scale":{"X":1.0,"Y":1.0,"Z":1.0},"angle":{"X":0.0,"Y":0.0,"Z":0.0},"rotation":{"X":0.0,"Y":0.0,"Z":0.0},"revolution":{"X":0.0,"Y":0.0,"Z":0.0},"revolutionCenter":{"X":0.0,"Y":0.0,"Z":0.0},"yMove":{"X":0.0,"Y":0.0,"Z":0.0},"xMove":{"X":0.0,"Y":0.0,"Z":0.0},"yScale":{"X":0.0,"Y":0.0,"Z":0.0},"xzScale":{"X":0.0,"Y":0.0,"Z":0.0},"paths":[],"pathV":{"X":0.0,"Y":0.0,"Z":0.0},"isStatic":false},{"wave":6,"propType":8,"colorInt":0,"oriY":0.14,"pos":{"X":1.04356635,"Y":0.14,"Z":-1.32707214},"scale":{"X":1.0,"Y":1.0,"Z":1.0},"angle":{"X":0.0,"Y":0.0,"Z":0.0},"rotation":{"X":0.0,"Y":0.0,"Z":0.0},"revolution":{"X":0.0,"Y":0.0,"Z":0.0},"revolutionCenter":{"X":0.0,"Y":0.0,"Z":0.0},"yMove":{"X":0.0,"Y":0.0,"Z":0.0},"xMove":{"X":0.0,"Y":0.0,"Z":0.0},"yScale":{"X":0.0,"Y":0.0,"Z":0.0},"xzScale":{"X":0.0,"Y":0.0,"Z":0.0},"paths":[],"pathV":{"X":0.0,"Y":0.0,"Z":0.0},"isStatic":false},{"wave":6,"propType":8,"colorInt":0,"oriY":0.14,"pos":{"X":0.5775076,"Y":0.14,"Z":-2.015503},"scale":{"X":1.0,"Y":1.0,"Z":1.0},"angle":{"X":0.0,"Y":0.0,"Z":0.0},"rotation":{"X":0.0,"Y":0.0,"Z":0.0},"revolution":{"X":0.0,"Y":0.0,"Z":0.0},"revolutionCenter":{"X":0.0,"Y":0.0,"Z":0.0},"yMove":{"X":0.0,"Y":0.0,"Z":0.0},"xMove":{"X":0.0,"Y":0.0,"Z":0.0},"yScale":{"X":0.0,"Y":0.0,"Z":0.0},"xzScale":{"X":0.0,"Y":0.0,"Z":0.0},"paths":[],"pathV":{"X":0.0,"Y":0.0,"Z":0.0},"isStatic":false},{"wave":6,"propType":8,"colorInt":0,"oriY":0.14,"pos":{"X":0.5065855,"Y":0.14,"Z":-2.504425},"scale":{"X":1.0,"Y":1.0,"Z":1.0},"angle":{"X":0.0,"Y":0.0,"Z":0.0},"rotation":{"X":0.0,"Y":0.0,"Z":0.0},"revolution":{"X":0.0,"Y":0.0,"Z":0.0},"revolutionCenter":{"X":0.0,"Y":0.0,"Z":0.0},"yMove":{"X":0.0,"Y":0.0,"Z":0.0},"xMove":{"X":0.0,"Y":0.0,"Z":0.0},"yScale":{"X":0.0,"Y":0.0,"Z":0.0},"xzScale":{"X":0.0,"Y":0.0,"Z":0.0},"paths":[],"pathV":{"X":0.0,"Y":0.0,"Z":0.0},"isStatic":false},{"wave":6,"propType":8,"colorInt":0,"oriY":0.14,"pos":{"X":1.59067869,"Y":0.14,"Z":-1.27716064},"scale":{"X":1.0,"Y":1.0,"Z":1.0},"angle":{"X":0.0,"Y":0.0,"Z":0.0},"rotation":{"X":0.0,"Y":0.0,"Z":0.0},"revolution":{"X":0.0,"Y":0.0,"Z":0.0},"revolutionCenter":{"X":0.0,"Y":0.0,"Z":0.0},"yMove":{"X":0.0,"Y":0.0,"Z":0.0},"xMove":{"X":0.0,"Y":0.0,"Z":0.0},"yScale":{"X":0.0,"Y":0.0,"Z":0.0},"xzScale":{"X":0.0,"Y":0.0,"Z":0.0},"paths":[],"pathV":{"X":0.0,"Y":0.0,"Z":0.0},"isStatic":false},{"wave":6,"propType":8,"colorInt":0,"oriY":0.14,"pos":{"X":1.40830779,"Y":0.14,"Z":-0.7184143},"scale":{"X":1.0,"Y":1.0,"Z":1.0},"angle":{"X":0.0,"Y":0.0,"Z":0.0},"rotation":{"X":0.0,"Y":0.0,"Z":0.0},"revolution":{"X":0.0,"Y":0.0,"Z":0.0},"revolutionCenter":{"X":0.0,"Y":0.0,"Z":0.0},"yMove":{"X":0.0,"Y":0.0,"Z":0.0},"xMove":{"X":0.0,"Y":0.0,"Z":0.0},"yScale":{"X":0.0,"Y":0.0,"Z":0.0},"xzScale":{"X":0.0,"Y":0.0,"Z":0.0},"paths":[],"pathV":{"X":0.0,"Y":0.0,"Z":0.0},"isStatic":false}]}]}