{"level":27,"maxWave":7,"propList":[{"wave":1,"propType":3,"colorInt":0,"oriY":0.0,"pos":{"X":-2.501301,"Y":0.0,"Z":-5.86305237},"scale":{"X":2.0,"Y":2.0,"Z":2.0},"angle":{"X":0.0,"Y":0.0,"Z":0.0},"rotation":{"X":0.0,"Y":0.0,"Z":0.0},"revolution":{"X":0.0,"Y":0.0,"Z":0.0},"revolutionCenter":{"X":0.0,"Y":0.0,"Z":0.0},"yMove":{"X":0.0,"Y":0.0,"Z":0.0},"xMove":{"X":0.0,"Y":0.0,"Z":0.0},"yScale":{"X":0.0,"Y":0.0,"Z":0.0},"xzScale":{"X":0.0,"Y":0.0,"Z":0.0},"paths":[],"pathV":{"X":0.0,"Y":0.0,"Z":0.0},"isStatic":true},{"wave":1,"propType":3,"colorInt":3,"oriY":0.0,"pos":{"X":-1.72945285,"Y":0.0,"Z":-2.56271362},"scale":{"X":1.0,"Y":1.0,"Z":1.0},"angle":{"X":0.0,"Y":0.0,"Z":0.0},"rotation":{"X":0.0,"Y":0.0,"Z":0.0},"revolution":{"X":0.0,"Y":0.0,"Z":0.0},"revolutionCenter":{"X":0.0,"Y":0.0,"Z":0.0},"yMove":{"X":0.0,"Y":0.0,"Z":0.0},"xMove":{"X":0.0,"Y":0.0,"Z":0.0},"yScale":{"X":0.0,"Y":0.0,"Z":0.0},"xzScale":{"X":0.0,"Y":0.0,"Z":0.0},"paths":[],"pathV":{"X":0.0,"Y":0.0,"Z":0.0},"isStatic":true},{"wave":1,"propType":3,"colorInt":2,"oriY":0.0,"pos":{"X":2.26730156,"Y":0.0,"Z":-5.236191},"scale":{"X":1.0,"Y":1.0,"Z":1.0},"angle":{"X":0.0,"Y":0.0,"Z":0.0},"rotation":{"X":0.0,"Y":0.0,"Z":0.0},"revolution":{"X":0.0,"Y":0.0,"Z":0.0},"revolutionCenter":{"X":0.0,"Y":0.0,"Z":0.0},"yMove":{"X":0.0,"Y":0.0,"Z":0.0},"xMove":{"X":0.0,"Y":0.0,"Z":0.0},"yScale":{"X":0.0,"Y":0.0,"Z":0.0},"xzScale":{"X":0.0,"Y":0.0,"Z":0.0},"paths":[],"pathV":{"X":0.0,"Y":0.0,"Z":0.0},"isStatic":true},{"wave":1,"propType":3,"colorInt":4,"oriY":0.0,"pos":{"X":-0.0126671717,"Y":0.0,"Z":1.5736084},"scale":{"X":1.0,"Y":1.0,"Z":1.0},"angle":{"X":0.0,"Y":0.0,"Z":0.0},"rotation":{"X":0.0,"Y":0.0,"Z":0.0},"revolution":{"X":0.0,"Y":0.0,"Z":0.0},"revolutionCenter":{"X":0.0,"Y":0.0,"Z":0.0},"yMove":{"X":0.0,"Y":0.0,"Z":0.0},"xMove":{"X":0.0,"Y":0.0,"Z":0.0},"yScale":{"X":0.0,"Y":0.0,"Z":0.0},"xzScale":{"X":0.0,"Y":0.0,"Z":0.0},"paths":[],"pathV":{"X":0.0,"Y":0.0,"Z":0.0},"isStatic":true},{"wave":1,"propType":3,"colorInt":5,"oriY":0.0,"pos":{"X":1.69636977,"Y":0.0,"Z":0.7784271},"scale":{"X":1.0,"Y":1.0,"Z":1.0},"angle":{"X":0.0,"Y":0.0,"Z":0.0},"rotation":{"X":0.0,"Y":0.0,"Z":0.0},"revolution":{"X":0.0,"Y":0.0,"Z":0.0},"revolutionCenter":{"X":0.0,"Y":0.0,"Z":0.0},"yMove":{"X":0.0,"Y":0.0,"Z":0.0},"xMove":{"X":0.0,"Y":0.0,"Z":0.0},"yScale":{"X":0.0,"Y":0.0,"Z":0.0},"xzScale":{"X":0.0,"Y":0.0,"Z":0.0},"paths":[],"pathV":{"X":0.0,"Y":0.0,"Z":0.0},"isStatic":true},{"wave":1,"propType":3,"colorInt":4,"oriY":0.0,"pos":{"X":-0.030182831,"Y":0.0,"Z":-3.38027954},"scale":{"X":1.0,"Y":1.0,"Z":1.0},"angle":{"X":0.0,"Y":0.0,"Z":0.0},"rotation":{"X":0.0,"Y":0.0,"Z":0.0},"revolution":{"X":0.0,"Y":0.0,"Z":0.0},"revolutionCenter":{"X":0.0,"Y":0.0,"Z":0.0},"yMove":{"X":0.0,"Y":0.0,"Z":0.0},"xMove":{"X":0.0,"Y":0.0,"Z":0.0},"yScale":{"X":0.0,"Y":0.0,"Z":0.0},"xzScale":{"X":0.0,"Y":0.0,"Z":0.0},"paths":[],"pathV":{"X":0.0,"Y":0.0,"Z":0.0},"isStatic":true},{"wave":1,"propType":3,"colorInt":2,"oriY":0.0,"pos":{"X":1.72977531,"Y":0.0,"Z":-2.50645447},"scale":{"X":1.0,"Y":1.0,"Z":1.0},"angle":{"X":0.0,"Y":0.0,"Z":0.0},"rotation":{"X":0.0,"Y":0.0,"Z":0.0},"revolution":{"X":0.0,"Y":0.0,"Z":0.0},"revolutionCenter":{"X":0.0,"Y":0.0,"Z":0.0},"yMove":{"X":0.0,"Y":0.0,"Z":0.0},"xMove":{"X":0.0,"Y":0.0,"Z":0.0},"yScale":{"X":0.0,"Y":0.0,"Z":0.0},"xzScale":{"X":0.0,"Y":0.0,"Z":0.0},"paths":[],"pathV":{"X":0.0,"Y":0.0,"Z":0.0},"isStatic":true},{"wave":1,"propType":0,"colorInt":0,"oriY":0.0,"pos":{"X":1.0540719,"Y":0.0,"Z":4.588806},"scale":{"X":1.0,"Y":1.0,"Z":1.0},"angle":{"X":0.0,"Y":0.0,"Z":0.0},"rotation":{"X":0.0,"Y":0.0,"Z":0.0},"revolution":{"X":0.0,"Y":0.0,"Z":0.0},"revolutionCenter":{"X":0.0,"Y":0.0,"Z":0.0},"yMove":{"X":0.0,"Y":0.0,"Z":0.0},"xMove":{"X":0.0,"Y":0.0,"Z":0.0},"yScale":{"X":0.0,"Y":0.0,"Z":0.0},"xzScale":{"X":0.0,"Y":0.0,"Z":0.0},"paths":[],"pathV":{"X":0.0,"Y":0.0,"Z":0.0},"isStatic":true},{"wave":1,"propType":2,"colorInt":0,"oriY":0.0,"pos":{"X":-0.166895717,"Y":0.0,"Z":-5.19950867},"scale":{"X":1.0,"Y":1.0,"Z":1.0},"angle":{"X":0.0,"Y":0.0,"Z":0.0},"rotation":{"X":0.0,"Y":0.0,"Z":0.0},"revolution":{"X":0.0,"Y":0.0,"Z":0.0},"revolutionCenter":{"X":0.0,"Y":0.0,"Z":0.0},"yMove":{"X":0.0,"Y":0.0,"Z":0.0},"xMove":{"X":0.0,"Y":0.0,"Z":0.0},"yScale":{"X":0.0,"Y":0.0,"Z":0.0},"xzScale":{"X":0.0,"Y":0.0,"Z":0.0},"paths":[],"pathV":{"X":0.0,"Y":0.0,"Z":0.0},"isStatic":true},{"wave":1,"propType":3,"colorInt":4,"oriY":0.0,"pos":{"X":-1.66770172,"Y":0.0,"Z":0.856842041},"scale":{"X":1.0,"Y":1.0,"Z":1.0},"angle":{"X":0.0,"Y":0.0,"Z":0.0},"rotation":{"X":0.0,"Y":0.0,"Z":0.0},"revolution":{"X":0.0,"Y":0.0,"Z":0.0},"revolutionCenter":{"X":0.0,"Y":0.0,"Z":0.0},"yMove":{"X":0.0,"Y":0.0,"Z":0.0},"xMove":{"X":0.0,"Y":0.0,"Z":0.0},"yScale":{"X":0.0,"Y":0.0,"Z":0.0},"xzScale":{"X":0.0,"Y":0.0,"Z":0.0},"paths":[],"pathV":{"X":0.0,"Y":0.0,"Z":0.0},"isStatic":true},{"wave":1,"propType":3,"colorInt":0,"oriY":0.0,"pos":{"X":-1.9250958,"Y":0.0,"Z":4.288971},"scale":{"X":1.0,"Y":1.0,"Z":1.0},"angle":{"X":0.0,"Y":0.0,"Z":0.0},"rotation":{"X":0.0,"Y":0.0,"Z":0.0},"revolution":{"X":0.0,"Y":0.0,"Z":0.0},"revolutionCenter":{"X":0.0,"Y":0.0,"Z":0.0},"yMove":{"X":0.0,"Y":0.0,"Z":0.0},"xMove":{"X":0.0,"Y":0.0,"Z":0.0},"yScale":{"X":0.0,"Y":0.0,"Z":0.0},"xzScale":{"X":0.0,"Y":0.0,"Z":0.0},"paths":[],"pathV":{"X":0.0,"Y":0.0,"Z":0.0},"isStatic":true},{"wave":1,"propType":3,"colorInt":0,"oriY":0.0,"pos":{"X":-1.31605184,"Y":0.0,"Z":4.015793},"scale":{"X":1.0,"Y":1.0,"Z":1.0},"angle":{"X":0.0,"Y":0.0,"Z":0.0},"rotation":{"X":0.0,"Y":0.0,"Z":0.0},"revolution":{"X":0.0,"Y":0.0,"Z":0.0},"revolutionCenter":{"X":0.0,"Y":0.0,"Z":0.0},"yMove":{"X":0.0,"Y":0.0,"Z":0.0},"xMove":{"X":0.0,"Y":0.0,"Z":0.0},"yScale":{"X":0.0,"Y":0.0,"Z":0.0},"xzScale":{"X":0.0,"Y":0.0,"Z":0.0},"paths":[],"pathV":{"X":0.0,"Y":0.0,"Z":0.0},"isStatic":true},{"wave":8,"propType":1,"colorInt":0,"oriY":0.0,"pos":{"X":-0.172239065,"Y":0.0,"Z":-4.85917664},"scale":{"X":1.0,"Y":1.0,"Z":1.0},"angle":{"X":0.0,"Y":0.0,"Z":0.0},"rotation":{"X":0.0,"Y":0.0,"Z":0.0},"revolution":{"X":0.0,"Y":0.0,"Z":0.0},"revolutionCenter":{"X":0.0,"Y":0.0,"Z":0.0},"yMove":{"X":0.0,"Y":0.0,"Z":0.0},"xMove":{"X":0.0,"Y":0.0,"Z":0.0},"yScale":{"X":0.0,"Y":0.0,"Z":0.0},"xzScale":{"X":0.0,"Y":0.0,"Z":0.0},"paths":[],"pathV":{"X":0.0,"Y":0.0,"Z":0.0},"isStatic":true}],"waveList":[{"wave":1,"propList":[{"wave":1,"propType":8,"colorInt":0,"oriY":0.14,"pos":{"X":1.56395066,"Y":0.14,"Z":-0.8672333},"scale":{"X":1.0,"Y":1.0,"Z":1.0},"angle":{"X":0.0,"Y":0.0,"Z":0.0},"rotation":{"X":0.0,"Y":0.0,"Z":0.0},"revolution":{"X":0.0,"Y":0.0,"Z":0.0},"revolutionCenter":{"X":0.0,"Y":0.0,"Z":0.0},"yMove":{"X":0.0,"Y":0.0,"Z":0.0},"xMove":{"X":0.0,"Y":0.0,"Z":0.0},"yScale":{"X":0.0,"Y":0.0,"Z":0.0},"xzScale":{"X":0.0,"Y":0.0,"Z":0.0},"paths":[],"pathV":{"X":0.0,"Y":0.0,"Z":0.0},"isStatic":false},{"wave":1,"propType":8,"colorInt":0,"oriY":0.14,"pos":{"X":1.19069326,"Y":0.14,"Z":-0.857605},"scale":{"X":1.0,"Y":1.0,"Z":1.0},"angle":{"X":0.0,"Y":0.0,"Z":0.0},"rotation":{"X":0.0,"Y":0.0,"Z":0.0},"revolution":{"X":0.0,"Y":0.0,"Z":0.0},"revolutionCenter":{"X":0.0,"Y":0.0,"Z":0.0},"yMove":{"X":0.0,"Y":0.0,"Z":0.0},"xMove":{"X":0.0,"Y":0.0,"Z":0.0},"yScale":{"X":0.0,"Y":0.0,"Z":0.0},"xzScale":{"X":0.0,"Y":0.0,"Z":0.0},"paths":[],"pathV":{"X":0.0,"Y":0.0,"Z":0.0},"isStatic":false},{"wave":1,"propType":8,"colorInt":0,"oriY":0.14,"pos":{"X":1.94733918,"Y":0.14,"Z":-0.8670807},"scale":{"X":1.0,"Y":1.0,"Z":1.0},"angle":{"X":0.0,"Y":0.0,"Z":0.0},"rotation":{"X":0.0,"Y":0.0,"Z":0.0},"revolution":{"X":0.0,"Y":0.0,"Z":0.0},"revolutionCenter":{"X":0.0,"Y":0.0,"Z":0.0},"yMove":{"X":0.0,"Y":0.0,"Z":0.0},"xMove":{"X":0.0,"Y":0.0,"Z":0.0},"yScale":{"X":0.0,"Y":0.0,"Z":0.0},"xzScale":{"X":0.0,"Y":0.0,"Z":0.0},"paths":[],"pathV":{"X":0.0,"Y":0.0,"Z":0.0},"isStatic":false}]},{"wave":3,"propList":[{"wave":3,"propType":9,"colorInt":0,"oriY":0.05,"pos":{"X":1.67535877,"Y":0.05,"Z":-1.08517456},"scale":{"X":1.0,"Y":1.0,"Z":1.0},"angle":{"X":0.0,"Y":0.0,"Z":0.0},"rotation":{"X":0.0,"Y":0.0,"Z":0.0},"revolution":{"X":0.0,"Y":0.0,"Z":0.0},"revolutionCenter":{"X":0.0,"Y":0.0,"Z":0.0},"yMove":{"X":0.0,"Y":0.0,"Z":0.0},"xMove":{"X":0.0,"Y":0.0,"Z":0.0},"yScale":{"X":0.0,"Y":0.0,"Z":0.0},"xzScale":{"X":0.0,"Y":0.0,"Z":0.0},"paths":[],"pathV":{"X":0.0,"Y":0.0,"Z":0.0},"isStatic":false},{"wave":3,"propType":9,"colorInt":0,"oriY":0.05,"pos":{"X":1.6783787,"Y":0.05,"Z":-0.6783142},"scale":{"X":1.0,"Y":1.0,"Z":1.0},"angle":{"X":0.0,"Y":0.0,"Z":0.0},"rotation":{"X":0.0,"Y":0.0,"Z":0.0},"revolution":{"X":0.0,"Y":0.0,"Z":0.0},"revolutionCenter":{"X":0.0,"Y":0.0,"Z":0.0},"yMove":{"X":0.0,"Y":0.0,"Z":0.0},"xMove":{"X":0.0,"Y":0.0,"Z":0.0},"yScale":{"X":0.0,"Y":0.0,"Z":0.0},"xzScale":{"X":0.0,"Y":0.0,"Z":0.0},"paths":[],"pathV":{"X":0.0,"Y":0.0,"Z":0.0},"isStatic":false}]},{"wave":2,"propList":[{"wave":2,"propType":9,"colorInt":0,"oriY":0.05,"pos":{"X":-1.72433984,"Y":0.05,"Z":-1.11914063},"scale":{"X":1.0,"Y":1.0,"Z":1.0},"angle":{"X":0.0,"Y":0.0,"Z":0.0},"rotation":{"X":0.0,"Y":0.0,"Z":0.0},"revolution":{"X":0.0,"Y":0.0,"Z":0.0},"revolutionCenter":{"X":0.0,"Y":0.0,"Z":0.0},"yMove":{"X":0.0,"Y":0.0,"Z":0.0},"xMove":{"X":0.0,"Y":0.0,"Z":0.0},"yScale":{"X":0.0,"Y":0.0,"Z":0.0},"xzScale":{"X":0.0,"Y":0.0,"Z":0.0},"paths":[],"pathV":{"X":0.0,"Y":0.0,"Z":0.0},"isStatic":false},{"wave":2,"propType":8,"colorInt":0,"oriY":0.14,"pos":{"X":-1.738998,"Y":0.14,"Z":-0.6623535},"scale":{"X":1.0,"Y":1.0,"Z":1.0},"angle":{"X":0.0,"Y":0.0,"Z":0.0},"rotation":{"X":0.0,"Y":0.0,"Z":0.0},"revolution":{"X":0.0,"Y":0.0,"Z":0.0},"revolutionCenter":{"X":0.0,"Y":0.0,"Z":0.0},"yMove":{"X":0.0,"Y":0.0,"Z":0.0},"xMove":{"X":0.0,"Y":0.0,"Z":0.0},"yScale":{"X":0.0,"Y":0.0,"Z":0.0},"xzScale":{"X":0.0,"Y":0.0,"Z":0.0},"paths":[],"pathV":{"X":0.0,"Y":0.0,"Z":0.0},"isStatic":false}]},{"wave":4,"propList":[{"wave":4,"propType":8,"colorInt":0,"oriY":0.14,"pos":{"X":-1.73252332,"Y":0.14,"Z":2.05540466},"scale":{"X":1.0,"Y":1.0,"Z":1.0},"angle":{"X":0.0,"Y":0.0,"Z":0.0},"rotation":{"X":0.0,"Y":0.0,"Z":0.0},"revolution":{"X":0.0,"Y":0.0,"Z":0.0},"revolutionCenter":{"X":0.0,"Y":0.0,"Z":0.0},"yMove":{"X":0.0,"Y":0.0,"Z":0.0},"xMove":{"X":0.0,"Y":0.0,"Z":0.0},"yScale":{"X":0.0,"Y":0.0,"Z":0.0},"xzScale":{"X":0.0,"Y":0.0,"Z":0.0},"paths":[],"pathV":{"X":0.0,"Y":0.0,"Z":0.0},"isStatic":false},{"wave":4,"propType":8,"colorInt":0,"oriY":0.14,"pos":{"X":-1.1955421,"Y":0.14,"Z":2.44454956},"scale":{"X":1.0,"Y":1.0,"Z":1.0},"angle":{"X":0.0,"Y":0.0,"Z":0.0},"rotation":{"X":0.0,"Y":0.0,"Z":0.0},"revolution":{"X":0.0,"Y":0.0,"Z":0.0},"revolutionCenter":{"X":0.0,"Y":0.0,"Z":0.0},"yMove":{"X":0.0,"Y":0.0,"Z":0.0},"xMove":{"X":0.0,"Y":0.0,"Z":0.0},"yScale":{"X":0.0,"Y":0.0,"Z":0.0},"xzScale":{"X":0.0,"Y":0.0,"Z":0.0},"paths":[],"pathV":{"X":0.0,"Y":0.0,"Z":0.0},"isStatic":false},{"wave":4,"propType":8,"colorInt":0,"oriY":0.14,"pos":{"X":-1.45896649,"Y":0.14,"Z":2.24501038},"scale":{"X":1.0,"Y":1.0,"Z":1.0},"angle":{"X":0.0,"Y":0.0,"Z":0.0},"rotation":{"X":0.0,"Y":0.0,"Z":0.0},"revolution":{"X":0.0,"Y":0.0,"Z":0.0},"revolutionCenter":{"X":0.0,"Y":0.0,"Z":0.0},"yMove":{"X":0.0,"Y":0.0,"Z":0.0},"xMove":{"X":0.0,"Y":0.0,"Z":0.0},"yScale":{"X":0.0,"Y":0.0,"Z":0.0},"xzScale":{"X":0.0,"Y":0.0,"Z":0.0},"paths":[],"pathV":{"X":0.0,"Y":0.0,"Z":0.0},"isStatic":false}]},{"wave":5,"propList":[{"wave":5,"propType":8,"colorInt":0,"oriY":0.14,"pos":{"X":0.7769598,"Y":0.14,"Z":1.29931641},"scale":{"X":1.0,"Y":1.0,"Z":1.0},"angle":{"X":0.0,"Y":0.0,"Z":0.0},"rotation":{"X":0.0,"Y":0.0,"Z":0.0},"revolution":{"X":0.0,"Y":0.0,"Z":0.0},"revolutionCenter":{"X":0.0,"Y":0.0,"Z":0.0},"yMove":{"X":0.0,"Y":0.0,"Z":0.0},"xMove":{"X":0.0,"Y":0.0,"Z":0.0},"yScale":{"X":0.0,"Y":0.0,"Z":0.0},"xzScale":{"X":0.0,"Y":0.0,"Z":0.0},"paths":[],"pathV":{"X":0.0,"Y":0.0,"Z":0.0},"isStatic":false},{"wave":5,"propType":8,"colorInt":0,"oriY":0.14,"pos":{"X":1.10080111,"Y":0.14,"Z":1.10310364},"scale":{"X":1.0,"Y":1.0,"Z":1.0},"angle":{"X":0.0,"Y":0.0,"Z":0.0},"rotation":{"X":0.0,"Y":0.0,"Z":0.0},"revolution":{"X":0.0,"Y":0.0,"Z":0.0},"revolutionCenter":{"X":0.0,"Y":0.0,"Z":0.0},"yMove":{"X":0.0,"Y":0.0,"Z":0.0},"xMove":{"X":0.0,"Y":0.0,"Z":0.0},"yScale":{"X":0.0,"Y":0.0,"Z":0.0},"xzScale":{"X":0.0,"Y":0.0,"Z":0.0},"paths":[],"pathV":{"X":0.0,"Y":0.0,"Z":0.0},"isStatic":false},{"wave":5,"propType":8,"colorInt":0,"oriY":0.14,"pos":{"X":1.1310842,"Y":0.14,"Z":-2.82450867},"scale":{"X":1.0,"Y":1.0,"Z":1.0},"angle":{"X":0.0,"Y":0.0,"Z":0.0},"rotation":{"X":0.0,"Y":0.0,"Z":0.0},"revolution":{"X":0.0,"Y":0.0,"Z":0.0},"revolutionCenter":{"X":0.0,"Y":0.0,"Z":0.0},"yMove":{"X":0.0,"Y":0.0,"Z":0.0},"xMove":{"X":0.0,"Y":0.0,"Z":0.0},"yScale":{"X":0.0,"Y":0.0,"Z":0.0},"xzScale":{"X":0.0,"Y":0.0,"Z":0.0},"paths":[],"pathV":{"X":0.0,"Y":0.0,"Z":0.0},"isStatic":false},{"wave":5,"propType":8,"colorInt":0,"oriY":0.14,"pos":{"X":0.836831,"Y":0.14,"Z":-3.020874},"scale":{"X":1.0,"Y":1.0,"Z":1.0},"angle":{"X":0.0,"Y":0.0,"Z":0.0},"rotation":{"X":0.0,"Y":0.0,"Z":0.0},"revolution":{"X":0.0,"Y":0.0,"Z":0.0},"revolutionCenter":{"X":0.0,"Y":0.0,"Z":0.0},"yMove":{"X":0.0,"Y":0.0,"Z":0.0},"xMove":{"X":0.0,"Y":0.0,"Z":0.0},"yScale":{"X":0.0,"Y":0.0,"Z":0.0},"xzScale":{"X":0.0,"Y":0.0,"Z":0.0},"paths":[],"pathV":{"X":0.0,"Y":0.0,"Z":0.0},"isStatic":false},{"wave":5,"propType":8,"colorInt":0,"oriY":0.14,"pos":{"X":-0.8036983,"Y":0.14,"Z":-3.13870239},"scale":{"X":1.0,"Y":1.0,"Z":1.0},"angle":{"X":0.0,"Y":0.0,"Z":0.0},"rotation":{"X":0.0,"Y":0.0,"Z":0.0},"revolution":{"X":0.0,"Y":0.0,"Z":0.0},"revolutionCenter":{"X":0.0,"Y":0.0,"Z":0.0},"yMove":{"X":0.0,"Y":0.0,"Z":0.0},"xMove":{"X":0.0,"Y":0.0,"Z":0.0},"yScale":{"X":0.0,"Y":0.0,"Z":0.0},"xzScale":{"X":0.0,"Y":0.0,"Z":0.0},"paths":[],"pathV":{"X":0.0,"Y":0.0,"Z":0.0},"isStatic":false},{"wave":5,"propType":8,"colorInt":0,"oriY":0.14,"pos":{"X":-1.117569,"Y":0.14,"Z":-2.95213318},"scale":{"X":1.0,"Y":1.0,"Z":1.0},"angle":{"X":0.0,"Y":0.0,"Z":0.0},"rotation":{"X":0.0,"Y":0.0,"Z":0.0},"revolution":{"X":0.0,"Y":0.0,"Z":0.0},"revolutionCenter":{"X":0.0,"Y":0.0,"Z":0.0},"yMove":{"X":0.0,"Y":0.0,"Z":0.0},"xMove":{"X":0.0,"Y":0.0,"Z":0.0},"yScale":{"X":0.0,"Y":0.0,"Z":0.0},"xzScale":{"X":0.0,"Y":0.0,"Z":0.0},"paths":[],"pathV":{"X":0.0,"Y":0.0,"Z":0.0},"isStatic":false},{"wave":5,"propType":8,"colorInt":0,"oriY":0.14,"pos":{"X":-0.787637,"Y":0.14,"Z":1.33532715},"scale":{"X":1.0,"Y":1.0,"Z":1.0},"angle":{"X":0.0,"Y":0.0,"Z":0.0},"rotation":{"X":0.0,"Y":0.0,"Z":0.0},"revolution":{"X":0.0,"Y":0.0,"Z":0.0},"revolutionCenter":{"X":0.0,"Y":0.0,"Z":0.0},"yMove":{"X":0.0,"Y":0.0,"Z":0.0},"xMove":{"X":0.0,"Y":0.0,"Z":0.0},"yScale":{"X":0.0,"Y":0.0,"Z":0.0},"xzScale":{"X":0.0,"Y":0.0,"Z":0.0},"paths":[],"pathV":{"X":0.0,"Y":0.0,"Z":0.0},"isStatic":false},{"wave":5,"propType":8,"colorInt":0,"oriY":0.14,"pos":{"X":-1.06679952,"Y":0.14,"Z":1.20768738},"scale":{"X":1.0,"Y":1.0,"Z":1.0},"angle":{"X":0.0,"Y":0.0,"Z":0.0},"rotation":{"X":0.0,"Y":0.0,"Z":0.0},"revolution":{"X":0.0,"Y":0.0,"Z":0.0},"revolutionCenter":{"X":0.0,"Y":0.0,"Z":0.0},"yMove":{"X":0.0,"Y":0.0,"Z":0.0},"xMove":{"X":0.0,"Y":0.0,"Z":0.0},"yScale":{"X":0.0,"Y":0.0,"Z":0.0},"xzScale":{"X":0.0,"Y":0.0,"Z":0.0},"paths":[],"pathV":{"X":0.0,"Y":0.0,"Z":0.0},"isStatic":false}]},{"wave":6,"propList":[{"wave":6,"propType":8,"colorInt":0,"oriY":0.14,"pos":{"X":-1.19377327,"Y":0.14,"Z":2.3658905},"scale":{"X":1.0,"Y":1.0,"Z":1.0},"angle":{"X":0.0,"Y":0.0,"Z":0.0},"rotation":{"X":0.0,"Y":0.0,"Z":0.0},"revolution":{"X":0.0,"Y":0.0,"Z":0.0},"revolutionCenter":{"X":0.0,"Y":0.0,"Z":0.0},"yMove":{"X":0.0,"Y":0.0,"Z":0.0},"xMove":{"X":0.0,"Y":0.0,"Z":0.0},"yScale":{"X":0.0,"Y":0.0,"Z":0.0},"xzScale":{"X":0.0,"Y":0.0,"Z":0.0},"paths":[],"pathV":{"X":0.0,"Y":0.0,"Z":0.0},"isStatic":false},{"wave":6,"propType":8,"colorInt":0,"oriY":0.14,"pos":{"X":1.1050539,"Y":0.14,"Z":-3.97744751},"scale":{"X":1.0,"Y":1.0,"Z":1.0},"angle":{"X":0.0,"Y":0.0,"Z":0.0},"rotation":{"X":0.0,"Y":0.0,"Z":0.0},"revolution":{"X":0.0,"Y":0.0,"Z":0.0},"revolutionCenter":{"X":0.0,"Y":0.0,"Z":0.0},"yMove":{"X":0.0,"Y":0.0,"Z":0.0},"xMove":{"X":0.0,"Y":0.0,"Z":0.0},"yScale":{"X":0.0,"Y":0.0,"Z":0.0},"xzScale":{"X":0.0,"Y":0.0,"Z":0.0},"paths":[],"pathV":{"X":0.0,"Y":0.0,"Z":0.0},"isStatic":false},{"wave":6,"propType":8,"colorInt":0,"oriY":0.14,"pos":{"X":1.36632669,"Y":0.14,"Z":-3.79055786},"scale":{"X":1.0,"Y":1.0,"Z":1.0},"angle":{"X":0.0,"Y":0.0,"Z":0.0},"rotation":{"X":0.0,"Y":0.0,"Z":0.0},"revolution":{"X":0.0,"Y":0.0,"Z":0.0},"revolutionCenter":{"X":0.0,"Y":0.0,"Z":0.0},"yMove":{"X":0.0,"Y":0.0,"Z":0.0},"xMove":{"X":0.0,"Y":0.0,"Z":0.0},"yScale":{"X":0.0,"Y":0.0,"Z":0.0},"xzScale":{"X":0.0,"Y":0.0,"Z":0.0},"paths":[],"pathV":{"X":0.0,"Y":0.0,"Z":0.0},"isStatic":false},{"wave":6,"propType":8,"colorInt":0,"oriY":0.14,"pos":{"X":-1.50548339,"Y":0.14,"Z":2.17974854},"scale":{"X":1.0,"Y":1.0,"Z":1.0},"angle":{"X":0.0,"Y":0.0,"Z":0.0},"rotation":{"X":0.0,"Y":0.0,"Z":0.0},"revolution":{"X":0.0,"Y":0.0,"Z":0.0},"revolutionCenter":{"X":0.0,"Y":0.0,"Z":0.0},"yMove":{"X":0.0,"Y":0.0,"Z":0.0},"xMove":{"X":0.0,"Y":0.0,"Z":0.0},"yScale":{"X":0.0,"Y":0.0,"Z":0.0},"xzScale":{"X":0.0,"Y":0.0,"Z":0.0},"paths":[],"pathV":{"X":0.0,"Y":0.0,"Z":0.0},"isStatic":false}]},{"wave":7,"propList":[{"wave":7,"propType":8,"colorInt":0,"oriY":0.14,"pos":{"X":0.3083756,"Y":0.14,"Z":0.444595337},"scale":{"X":1.0,"Y":1.0,"Z":1.0},"angle":{"X":0.0,"Y":0.0,"Z":0.0},"rotation":{"X":0.0,"Y":0.0,"Z":0.0},"revolution":{"X":0.0,"Y":0.0,"Z":0.0},"revolutionCenter":{"X":0.0,"Y":0.0,"Z":0.0},"yMove":{"X":0.0,"Y":0.0,"Z":0.0},"xMove":{"X":0.0,"Y":0.0,"Z":0.0},"yScale":{"X":0.0,"Y":0.0,"Z":0.0},"xzScale":{"X":0.0,"Y":0.0,"Z":0.0},"paths":[],"pathV":{"X":0.0,"Y":0.0,"Z":0.0},"isStatic":false},{"wave":7,"propType":9,"colorInt":0,"oriY":0.05,"pos":{"X":-0.0941448361,"Y":0.05,"Z":0.45098877},"scale":{"X":1.0,"Y":1.0,"Z":1.0},"angle":{"X":0.0,"Y":0.0,"Z":0.0},"rotation":{"X":0.0,"Y":0.0,"Z":0.0},"revolution":{"X":0.0,"Y":0.0,"Z":0.0},"revolutionCenter":{"X":-0.6686931,"Y":0.14,"Z":-1.057663},"yMove":{"X":0.0,"Y":0.0,"Z":0.0},"xMove":{"X":0.0,"Y":0.0,"Z":0.0},"yScale":{"X":0.0,"Y":0.0,"Z":0.0},"xzScale":{"X":0.0,"Y":0.0,"Z":0.0},"paths":[],"pathV":{"X":0.0,"Y":0.0,"Z":0.0},"isStatic":false},{"wave":7,"propType":8,"colorInt":0,"oriY":0.14,"pos":{"X":-0.487666368,"Y":0.14,"Z":0.468582153},"scale":{"X":1.0,"Y":1.0,"Z":1.0},"angle":{"X":0.0,"Y":0.0,"Z":0.0},"rotation":{"X":0.0,"Y":0.0,"Z":0.0},"revolution":{"X":0.0,"Y":0.0,"Z":0.0},"revolutionCenter":{"X":0.0,"Y":0.0,"Z":0.0},"yMove":{"X":0.0,"Y":0.0,"Z":0.0},"xMove":{"X":0.0,"Y":0.0,"Z":0.0},"yScale":{"X":0.0,"Y":0.0,"Z":0.0},"xzScale":{"X":0.0,"Y":0.0,"Z":0.0},"paths":[],"pathV":{"X":0.0,"Y":0.0,"Z":0.0},"isStatic":false}]}]}